SimpleRichTradingJournal/ABOUT.md
SimpleRichTradingJournal/__init__.py
SimpleRichTradingJournal/__main__.py
SimpleRichTradingJournal/main.py
SimpleRichTradingJournal/__env__/__init__.py
SimpleRichTradingJournal/__env__/_files.py
SimpleRichTradingJournal/__env__/call-gui-engine.txt
SimpleRichTradingJournal/__env__/colors.py
SimpleRichTradingJournal/__env__/plugin.py
SimpleRichTradingJournal/__env__/rconfig.py
SimpleRichTradingJournal/__env__/#demo/call-gui-engine.txt
SimpleRichTradingJournal/__env__/#demo/journal.pkl
SimpleRichTradingJournal/__env__/#demo/plugin.py
SimpleRichTradingJournal/__env__/#demo/rconfig.py
SimpleRichTradingJournal/__env__/#demo/files/clones/_ex1.png
SimpleRichTradingJournal/__env__/#demo/files/clones/_ex2.png
SimpleRichTradingJournal/__env__/#demo/files/clones/_ex3.png
SimpleRichTradingJournal/__env__/__pycache__/__init__.cpython-310.pyc
SimpleRichTradingJournal/__env__/__pycache__/_files.cpython-310.pyc
SimpleRichTradingJournal/__env__/__pycache__/plugin.cpython-310.pyc
SimpleRichTradingJournal/__env__/__pycache__/rconfig.cpython-310.pyc
SimpleRichTradingJournal/__env__/_upgrade/__init__.py
SimpleRichTradingJournal/__env__/_upgrade/__pycache__/__init__.cpython-310.pyc
SimpleRichTradingJournal/__ini__/__init__.py
SimpleRichTradingJournal/__ini__/cmdl.py
SimpleRichTradingJournal/__ini__/logtags.py
SimpleRichTradingJournal/__ini__/__pycache__/__init__.cpython-310.pyc
SimpleRichTradingJournal/__ini__/__pycache__/cmdl.cpython-310.pyc
SimpleRichTradingJournal/__ini__/__pycache__/logtags.cpython-310.pyc
SimpleRichTradingJournal/__pycache__/__init__.cpython-310.pyc
SimpleRichTradingJournal/__pycache__/main.cpython-310.pyc
SimpleRichTradingJournal/calc/__init__.py
SimpleRichTradingJournal/calc/log.py
SimpleRichTradingJournal/calc/utils.py
SimpleRichTradingJournal/calc/__pycache__/__init__.cpython-310.pyc
SimpleRichTradingJournal/calc/__pycache__/log.cpython-310.pyc
SimpleRichTradingJournal/calc/__pycache__/utils.cpython-310.pyc
simplerichtradingjournal-0.6.2.2.dist-info/licenses/LICENSE.txt
simplerichtradingjournal-0.6.2.2.dist-info/METADATA
simplerichtradingjournal-0.6.2.2.dist-info/WHEEL
simplerichtradingjournal-0.6.2.2.dist-info/entry_points.txt
simplerichtradingjournal-0.6.2.2.dist-info/top_level.txt
simplerichtradingjournal-0.6.2.2.dist-info/RECORD
