Metadata-Version: 2.4
Name: SimpleRichTradingJournal
Version: 0.6.2.2
Summary: Rich Trading Journal
Author-email: "Adrian F. Hoefflin" <srccircumflex-srtj@outlook.com>
License: CC BY-NC-ND 4.0
Project-URL: Homepage, https://simple-rich-trading-journal.github.io
Project-URL: Documentation, https://simple-rich-trading-journal.github.io
Project-URL: Repository, https://github.com/Simple-Rich-Trading-Journal/Simple-Rich-Trading-Journal
Project-URL: Issues, https://github.com/Simple-Rich-Trading-Journal/Simple-Rich-Trading-Journal/issues
Project-URL: Changelog, https://github.com/Simple-Rich-Trading-Journal/Simple-Rich-Trading-Journal#version-history
Keywords: trading,trading journal,trading log,trading protocol,finance,finance journal,finance log,finance protocol
Classifier: Development Status :: 4 - Beta
Classifier: Environment :: Console
Classifier: Environment :: Web Environment
Classifier: Framework :: Dash
Classifier: Intended Audience :: Developers
Classifier: Intended Audience :: End Users/Desktop
Classifier: Intended Audience :: Financial and Insurance Industry
Classifier: License :: Free for non-commercial use
Classifier: Natural Language :: English
Classifier: Programming Language :: Python :: 3.10
Classifier: Programming Language :: Python :: 3.11
Classifier: Programming Language :: Python :: 3.12
Classifier: Programming Language :: Python :: 3.13
Classifier: Programming Language :: Python :: 3.14
Classifier: Topic :: Database
Requires-Python: >=3.10
License-File: LICENSE.txt
Requires-Dist: plotly>=5.18.0
Requires-Dist: dash>=2.16.1
Requires-Dist: dash_ag_grid>=31.0.1
Requires-Dist: numpy>=1.26.3
Dynamic: license-file
